<?xml  version='1.0' encoding='UTF-8'?>
<com.jme3.scene.Node format_version='2' name='CSGSamples'>
    <transform class='com.jme3.math.Transform'>
        <translation class='com.jme3.math.Vector3f' y='0.0'/>
    </transform>
    <children>
    
        <!-- Normal -->
        <com.jme3.scene.Geometry name='Box1'
        		materialName='Textures/Debug/Normals.xml'>
            <transform class='com.jme3.math.Transform'>
                <translation class='com.jme3.math.Vector3f' x='0.0' y='0.0'/>
            </transform>
            <mesh class='net.wcomohundro.jme3.csg.shape.CSGCylinder'>
            	<lodFactors data='0.5 0.3 0.25 0.125' />
            </mesh>
        </com.jme3.scene.Geometry>
        <com.jme3.scene.Geometry name='Box2'
        		materialName='Textures/Debug/Normals.xml'>
            <transform class='com.jme3.math.Transform'>
                <translation class='com.jme3.math.Vector3f' x='0.0' y='0.0' z='-3.0'/>
            </transform>
            <mesh class='net.wcomohundro.jme3.csg.shape.CSGCylinder' axisSamples='16'>
            	<lodFactors data='0.5 0.3 0.25 0.125' />
            </mesh>
        </com.jme3.scene.Geometry>
        <com.jme3.scene.Geometry name='Box3'
        		materialName='Textures/Debug/Normals.xml'>
            <transform class='com.jme3.math.Transform'>
                <translation class='com.jme3.math.Vector3f' x='0.0' y='0.0' z='-6.0'/>
            </transform>
            <mesh class='net.wcomohundro.jme3.csg.shape.CSGCylinder' axisSamples='8'>
            	<lodFactors data='0.5 0.25'/>
            </mesh>
        </com.jme3.scene.Geometry>
        <com.jme3.scene.Geometry name='Box4'
        		materialName='Textures/Debug/Normals.xml'>
            <transform class='com.jme3.math.Transform'>
                <translation class='com.jme3.math.Vector3f' x='0.0' y='0.0' z='-9.0'/>
            </transform>
            <mesh class='net.wcomohundro.jme3.csg.shape.CSGCylinder' axisSamples='4'>
            	<lodFactors data='0.5' />
            </mesh>
        </com.jme3.scene.Geometry>
        <com.jme3.scene.Geometry name='Box5'
        		materialName='Textures/Debug/Normals.xml'>
            <transform class='com.jme3.math.Transform'>
                <translation class='com.jme3.math.Vector3f' x='0.0' y='0.0' z='-12.0'/>
            </transform>
            <mesh class='net.wcomohundro.jme3.csg.shape.CSGCylinder' axisSamples='2'>
                 <lodFactors data='0.5' />
            </mesh>
        </com.jme3.scene.Geometry>
        <com.jme3.scene.Geometry name='Box6'
        		materialName='Textures/Debug/Normals.xml'>
            <transform class='com.jme3.math.Transform'>
                <translation class='com.jme3.math.Vector3f' x='0.0' y='0.0' z='-15.0'/>
            </transform>
            <mesh class='net.wcomohundro.jme3.csg.shape.CSGCylinder' closed='false'>
                 <lodFactors data='0.5 0.3 0.25 0.125' />
            </mesh>
        </com.jme3.scene.Geometry>

        <!-- Wireframe -->
        <com.jme3.scene.Geometry name='Box1'
        		materialName='Textures/Debug/Wireframe.xml'>
            <transform class='com.jme3.math.Transform'>
                <translation class='com.jme3.math.Vector3f' x='3.0' y='0.0'/>
            </transform>
            <mesh class='net.wcomohundro.jme3.csg.shape.CSGCylinder'>
            	<lodFactors data='0.5 0.3 0.25 0.125' />
            </mesh>
        </com.jme3.scene.Geometry>

        <com.jme3.scene.Geometry name='Box2'
        		materialName='Textures/Debug/Wireframe.xml'>
            <transform class='com.jme3.math.Transform'>
                <translation class='com.jme3.math.Vector3f' x='3.0' y='0.0' z='-3.0'/>
            </transform>
            <mesh class='net.wcomohundro.jme3.csg.shape.CSGCylinder' axisSamples='16'>
            	<lodFactors data='0.5 0.3 0.25 0.125' />
            </mesh>
        </com.jme3.scene.Geometry>
        <com.jme3.scene.Geometry name='Box3'
        		materialName='Textures/Debug/Wireframe.xml'>
            <transform class='com.jme3.math.Transform'>
                <translation class='com.jme3.math.Vector3f' x='3.0' y='0.0' z='-6.0'/>
            </transform>
            <mesh class='net.wcomohundro.jme3.csg.shape.CSGCylinder' axisSamples='8'>
            	<lodFactors data='0.5 0.25' />
            </mesh>
        </com.jme3.scene.Geometry>
        <com.jme3.scene.Geometry name='Box4'
        		materialName='Textures/Debug/Wireframe.xml'>
            <transform class='com.jme3.math.Transform'>
                <translation class='com.jme3.math.Vector3f' x='3.0' y='0.0' z='-9.0'/>
            </transform>
            <mesh class='net.wcomohundro.jme3.csg.shape.CSGCylinder' axisSamples='4'>
            	<lodFactors data='0.5' />
            </mesh>
        </com.jme3.scene.Geometry>
        <com.jme3.scene.Geometry name='Box5'
        		materialName='Textures/Debug/Wireframe.xml'>
            <transform class='com.jme3.math.Transform'>
                <translation class='com.jme3.math.Vector3f' x='3.0' y='0.0' z='-12.0'/>
            </transform>
            <mesh class='net.wcomohundro.jme3.csg.shape.CSGCylinder' axisSamples='2'>
            	<lodFactors data='0.5' />
            </mesh>
        </com.jme3.scene.Geometry>
        <com.jme3.scene.Geometry name='Box6'
        		materialName='Textures/Debug/Wireframe.xml'>
            <transform class='com.jme3.math.Transform'>
                <translation class='com.jme3.math.Vector3f' x='3.0' y='0.0' z='-15.0'/>
            </transform>
            <mesh class='net.wcomohundro.jme3.csg.shape.CSGCylinder' closed='false'>
            	<lodFactors data='0.5 0.3 0.25 0.125' />
            </mesh>
        </com.jme3.scene.Geometry>

        <!-- Brickwall -->
        <com.jme3.scene.Geometry name='Box2'
        		materialName='Textures/BrickWall/BrickWall.xml'>
            <transform class='com.jme3.math.Transform'>
                <translation class='com.jme3.math.Vector3f' x='6.0' y='0.0'/>
            </transform>
            <mesh class='net.wcomohundro.jme3.csg.shape.CSGCylinder'>
            	<lodFactors data='0.5 0.3 0.25 0.125' />
            </mesh>
        </com.jme3.scene.Geometry>
        <com.jme3.scene.Geometry name='Box2'
        		materialName='Textures/BrickWall/BrickWall.xml'>
            <transform class='com.jme3.math.Transform'>
                <translation class='com.jme3.math.Vector3f' x='6.0' y='0.0' z='-3.0'/>
            </transform>
            <mesh class='net.wcomohundro.jme3.csg.shape.CSGCylinder' textureMode='UNIFORM'>
            	<lodFactors data='0.5 0.3 0.25 0.125' />
            </mesh>
        </com.jme3.scene.Geometry>
        <com.jme3.scene.Geometry name='Box2'
        		materialName='Textures/BrickWall/BrickWall.xml'>
            <transform class='com.jme3.math.Transform'>
                <translation class='com.jme3.math.Vector3f' x='6.0' y='0.0' z='-6.0'/>
            </transform>
            <mesh class='net.wcomohundro.jme3.csg.shape.CSGCylinder' textureMode='FLAT_LINEAR'>
            	<lodFactors data='0.5 0.3 0.25 0.125' />
            </mesh>
        </com.jme3.scene.Geometry>
        <com.jme3.scene.Geometry name='Box2'
        		materialName='Textures/BrickWall/BrickWall.xml'>
            <transform class='com.jme3.math.Transform'>
                <translation class='com.jme3.math.Vector3f' x='6.0' y='0.0' z='-9.0'/>
                <scale class='com.jme3.math.Vector3f' x='1.0' y='0.5' z='1.0'/>
            </transform>
            <mesh class='net.wcomohundro.jme3.csg.shape.CSGCylinder'>
            	<lodFactors data='0.5 0.3 0.25 0.125' />
            </mesh>
        </com.jme3.scene.Geometry>
        <com.jme3.scene.Geometry name='Box2'
        		materialName='Textures/BrickWall/BrickWall.xml'>
            <transform class='com.jme3.math.Transform'>
                <translation class='com.jme3.math.Vector3f' x='6.0' y='0.0' z='-12.0'/>
            </transform>
            <mesh class='net.wcomohundro.jme3.csg.shape.CSGCylinder' scaleSliceY='0.5'>
            	<lodFactors data='0.5 0.3 0.25 0.125' />
            </mesh>
        </com.jme3.scene.Geometry>
        <com.jme3.scene.Geometry name='Box2'
        		materialName='Textures/BrickWall/BrickWall.xml'>
            <transform class='com.jme3.math.Transform'>
                <translation class='com.jme3.math.Vector3f' x='6.0' y='0.0' z='-15.0'/>
            </transform>
            <mesh class='net.wcomohundro.jme3.csg.shape.CSGCylinder' twist='PI/2' scaleSliceY='0.5'>
            	<lodFactors data='0.5 0.3 0.25 0.125' />
            </mesh>
        </com.jme3.scene.Geometry>
        
   		<!-- Rock1 -->
        <com.jme3.scene.Geometry name='Box3'
        		materialName='Textures/Rock/Rock1.xml'>
            <transform class='com.jme3.math.Transform'>
                <translation class='com.jme3.math.Vector3f' x='9.0' y='0.0'/>
            </transform>
            <mesh class='net.wcomohundro.jme3.csg.shape.CSGCylinder'>
            	<lodFactors data='0.5 0.3 0.25 0.125' />
            </mesh>
        </com.jme3.scene.Geometry>  
        <com.jme3.scene.Geometry name='Box3'
        		materialName='Textures/Rock/Rock1.xml'>
            <transform class='com.jme3.math.Transform'>
                <translation class='com.jme3.math.Vector3f' x='9.0' y='0.0' z='-3.0'/>
            </transform>
            <mesh class='net.wcomohundro.jme3.csg.shape.CSGCylinder' textureMode='UNIFORM'>
            	<lodFactors data='0.5 0.3 0.25 0.125' />
            </mesh>
        </com.jme3.scene.Geometry>  
        
   		<!-- Rock1 -->
        <com.jme3.scene.Geometry name='Box4'
        		materialName='Textures/Rock/Rock2.xml'>
            <transform class='com.jme3.math.Transform'>
                <translation class='com.jme3.math.Vector3f' x='12.0' y='0.0'/>
            </transform>
            <mesh class='net.wcomohundro.jme3.csg.shape.CSGCylinder'>
            	<lodFactors data='0.5 0.3 0.25 0.125' />
            </mesh>
        </com.jme3.scene.Geometry>  
        <com.jme3.scene.Geometry name='Box4'
        		materialName='Textures/Rock/Rock2.xml'>
            <transform class='com.jme3.math.Transform'>
                <translation class='com.jme3.math.Vector3f' x='12.0' y='0.0' z='-3.0'/>
            </transform>
            <mesh class='net.wcomohundro.jme3.csg.shape.CSGCylinder' textureMode='UNIFORM'>
            	<lodFactors data='0.5 0.3 0.25 0.125' />
            </mesh>
        </com.jme3.scene.Geometry>  
?>
    </children>
</com.jme3.scene.Node>
